mseep_toolfront-0.2.16.dist-info/licenses/LICENSE
toolfront/__init__.py
toolfront/config.py
toolfront/mcp.py
toolfront/utils.py
toolfront/instructions/__init__.py
toolfront/instructions/ask.txt
toolfront/instructions/query.txt
toolfront/models/__init__.py
toolfront/models/api.py
toolfront/models/base.py
toolfront/models/database.py
toolfront/models/document.py
mseep_toolfront-0.2.16.dist-info/METADATA
mseep_toolfront-0.2.16.dist-info/WHEEL
mseep_toolfront-0.2.16.dist-info/entry_points.txt
mseep_toolfront-0.2.16.dist-info/top_level.txt
mseep_toolfront-0.2.16.dist-info/RECORD
